[
    {
        "full_name": "Kurt Cristan L. Bonrostro",
        "student_id": "2024 - 140318",
        "enrolled_block": "BSIT - 24",
        "pe_course": "pedu2",
        "workout_start": "10:17:36",
        "last_gym": "September 05, 2025 10:17:46",
        "workout_end": "10:17:46",
        "workout_time": 0.15,
        "completed_sessions": 3
    },
    {
        "full_name": "Dwight Joseph D. Fernandez",
        "student_id": "2024-140314",
        "enrolled_block": "BSIT242",
        "pe_course": "none",
        "workout_start": "09:18:08",
        "last_gym": "September 05, 2025 10:47:48",
        "workout_end": "10:47:48",
        "workout_time": 89.67,
        "completed_sessions": 5
    },
    {
        "full_name": "Kurt Cristan L. Bonrostro",
        "student_id": "2024 - 140318",
        "enrolled_block": "BSIT - 24",
        "pe_course": "pedu2",
        "workout_start": "10:17:53",
        "last_gym": "September 05, 2025 11:27:27",
        "workout_end": "11:27:27",
        "workout_time": 69.56,
        "completed_sessions": 4
    },
    {
        "full_name": "Jezron Cardona",
        "student_id": "2024-140197",
        "enrolled_block": "IT242",
        "pe_course": "none",
        "workout_start": "09:21:39",
        "last_gym": "September 05, 2025 11:29:34",
        "workout_end": "11:29:34",
        "workout_time": 127.92,
        "completed_sessions": 4
    },
    {
        "full_name": "Jonathan Mark Agbulos",
        "student_id": "2024-140293",
        "enrolled_block": "IT242",
        "pe_course": "pedu2",
        "workout_start": "10:12:32",
        "last_gym": "September 05, 2025 11:31:09",
        "workout_end": "11:31:09",
        "workout_time": 78.61,
        "completed_sessions": 3
    },
    {
        "full_name": "Ashlee Dan D. Esprecion ",
        "student_id": "2024-140180",
        "enrolled_block": "BSIT242",
        "pe_course": "none",
        "workout_start": "09:16:43",
        "last_gym": "September 05, 2025 11:41:20",
        "workout_end": "11:41:20",
        "workout_time": 144.6,
        "completed_sessions": 5
    },
    {
        "full_name": "Lance Gabriel M . Buncab",
        "student_id": "2024-140210",
        "enrolled_block": "SF241",
        "pe_course": "pedu1",
        "workout_start": "11:23:38",
        "last_gym": "September 05, 2025 11:41:20",
        "workout_end": "11:41:20",
        "workout_time": 17.69,
        "completed_sessions": 5
    },
    {
        "full_name": "Rei Khalil S. Galido",
        "student_id": "2024-140265",
        "enrolled_block": "IT242",
        "pe_course": "pedu2",
        "workout_start": "09:52:15",
        "last_gym": "September 05, 2025 11:41:20",
        "workout_end": "11:41:20",
        "workout_time": 109.08,
        "completed_sessions": 3
    },
    {
        "full_name": "Roman Rico B. Albania",
        "student_id": "2024-140320",
        "enrolled_block": "BSIT242",
        "pe_course": "pedu2",
        "workout_start": "09:16:36",
        "last_gym": "September 05, 2025 11:41:20",
        "workout_end": "11:41:20",
        "workout_time": 144.73,
        "completed_sessions": 2
    },
    {
        "full_name": "Patricia Marie D. Valera",
        "student_id": "2024-140240",
        "enrolled_block": "IT242",
        "pe_course": "pedu2",
        "workout_start": "09:16:50",
        "last_gym": "September 05, 2025 11:41:20",
        "workout_end": "11:41:20",
        "workout_time": 144.49,
        "completed_sessions": 3
    },
    {
        "full_name": "Gwyneth C. Salud",
        "student_id": "2024-140187",
        "enrolled_block": "IT242",
        "pe_course": "pedu2",
        "workout_start": "09:19:22",
        "last_gym": "September 05, 2025 11:41:20",
        "workout_end": "11:41:20",
        "workout_time": 141.97,
        "completed_sessions": 2
    },
    {
        "full_name": "Ni\u00f1a Arcel R. Ramos",
        "student_id": "2024-140196",
        "enrolled_block": "IT242",
        "pe_course": "pedu2",
        "workout_start": "10:12:13",
        "last_gym": "September 05, 2025 11:41:20",
        "workout_end": "11:41:20",
        "workout_time": 89.11,
        "completed_sessions": 2
    },
    {
        "full_name": "Wilte V. Dela Cruz",
        "student_id": "1364078561",
        "enrolled_block": "BSIT242",
        "pe_course": "pedu2",
        "workout_start": "10:26:05",
        "last_gym": "September 05, 2025 11:41:20",
        "workout_end": "11:41:20",
        "workout_time": 75.24,
        "completed_sessions": 2
    },
    {
        "full_name": "JOSHMAR CLAVERO",
        "student_id": "2024-140325",
        "enrolled_block": "IT242",
        "pe_course": "pedu2",
        "workout_start": "10:19:29",
        "last_gym": "September 05, 2025 11:41:20",
        "workout_end": "11:41:20",
        "workout_time": 81.84,
        "completed_sessions": 3
    },
    {
        "full_name": "Mark Benedict D. Ani",
        "student_id": "2024-140194",
        "enrolled_block": "BSIT242",
        "pe_course": "pedu2",
        "workout_start": "10:44:57",
        "last_gym": "September 05, 2025 11:41:20",
        "workout_end": "11:41:20",
        "workout_time": 56.38,
        "completed_sessions": 3
    }
]